.pre-commit-config.yaml
CHANGES.md
CONTRIBUTORS.md
DEVELOP.md
LICENSE.GPL
LICENSE.md
MANIFEST.in
README.md
pyproject.toml
setup.cfg
setup.py
src/collective/__init__.py
src/collective.hardening.egg-info/PKG-INFO
src/collective.hardening.egg-info/SOURCES.txt
src/collective.hardening.egg-info/dependency_links.txt
src/collective.hardening.egg-info/entry_points.txt
src/collective.hardening.egg-info/namespace_packages.txt
src/collective.hardening.egg-info/not-zip-safe
src/collective.hardening.egg-info/requires.txt
src/collective.hardening.egg-info/top_level.txt
src/collective/hardening/__init__.py
src/collective/hardening/configure.zcml
src/collective/hardening/interfaces.py
src/collective/hardening/profiles.zcml
src/collective/hardening/setuphandlers.py
src/collective/hardening/testing.py
src/collective/hardening/adapters/__init__.py
src/collective/hardening/adapters/configure.zcml
src/collective/hardening/adapters/primary_field.py
src/collective/hardening/controlpanel/__init__.py
src/collective/hardening/controlpanel/configure.zcml
src/collective/hardening/controlpanel/settings.py
src/collective/hardening/locales/en/LC_MESSAGES/collective.hardening.po
src/collective/hardening/profiles/default/browserlayer.xml
src/collective/hardening/profiles/default/catalog.xml
src/collective/hardening/profiles/default/controlpanel.xml
src/collective/hardening/profiles/default/metadata.xml
src/collective/hardening/profiles/default/rolemap.xml
src/collective/hardening/profiles/default/registry/main.xml
src/collective/hardening/profiles/default/registry/settings.xml
src/collective/hardening/profiles/uninstall/browserlayer.xml
src/collective/hardening/profiles/uninstall/controlpanel.xml
src/collective/hardening/profiles/uninstall/registry.xml
src/collective/hardening/subscribers/__init__.py
src/collective/hardening/subscribers/configure.zcml
src/collective/hardening/subscribers/files.py
src/collective/hardening/tests/__init__.py
src/collective/hardening/tests/test_setup.py