Metadata-Version: 2.1
Name: collective.hardening
Version: 0.0.1
Summary: An addon for hardening Plone
Home-page: https://github.com/collective/collective.hardening
Author: ale-rt
Author-email: alessandro.pisa@gmail.com
License: GPL version 2
Project-URL: PyPI, https://pypi.org/project/collective.hardening/
Project-URL: Source, https://github.com/collective/collective.hardening
Project-URL: Tracker, https://github.com/collective/collective.hardening/issues
Keywords: Python Plone CMS Hardening
Classifier: Development Status :: 3 - Alpha
Classifier: Environment :: Web Environment
Classifier: Framework :: Plone
Classifier: Framework :: Plone :: Addon
Classifier: Framework :: Plone :: 6.0
Classifier: Framework :: Plone :: 6.1
Classifier: Programming Language :: Python
Classifier: Programming Language :: Python :: 3.9
Classifier: Programming Language :: Python :: 3.10
Classifier: Programming Language :: Python :: 3.11
Classifier: Programming Language :: Python :: 3.12
Classifier: Programming Language :: Python :: 3.13
Classifier: Operating System :: OS Independent
Classifier: License :: OSI Approved :: GNU General Public License v2 (GPLv2)
Requires-Python: >=3.9
License-File: LICENSE.GPL
License-File: LICENSE.md
Requires-Dist: AccessControl
Requires-Dist: plone.api
Requires-Dist: plone.app.registry
Requires-Dist: plone.dexterity
Requires-Dist: plone.formwidget.namedfile
Requires-Dist: plone.memoize
Requires-Dist: plone.namedfile
Requires-Dist: plone.registry
Requires-Dist: plone.rfc822
Requires-Dist: plone.z3cform
Requires-Dist: Products.CMFPlone
Requires-Dist: Products.GenericSetup
Requires-Dist: setuptools
Requires-Dist: z3c.form
Requires-Dist: zExceptions
Requires-Dist: zope.component
Requires-Dist: zope.globalrequest
Requires-Dist: zope.i18nmessageid
Requires-Dist: zope.interface
Requires-Dist: zope.lifecycleevent
Requires-Dist: zope.publisher
Requires-Dist: zope.schema
Provides-Extra: test
Requires-Dist: plone.base; extra == "test"
Requires-Dist: plone.browserlayer; extra == "test"
Requires-Dist: plone.app.testing; extra == "test"
Requires-Dist: plone.app.contenttypes[test]; extra == "test"
